{
  "id": "f7b6c3d2-a1e5-4b3c-9d28-78326e69df28",
  "alias": "SendEmailWebPart",
  "componentType": "WebPart",
  "version": "2.0.0",
  "manifestVersion": 2,
  "requiresCustomScript": false,
  "supportedHosts": [
    "SharePointWebPart"
  ],
  "supportsThemeVariants": true,
  "preconfiguredEntries": [
    {
      "groupId": "5c03119e-3074-46fd-976b-c60198311f70",
      "group": {
        "default": "Other"
      },
      "title": {
        "default": "Send Email"
      },
      "description": {
        "default": "Sends an email using Microsoft Graph API"
      },
      "officeFabricIconFontName": "Mail",
      "properties": {}
    }
  ],
  "metadata": {
    "requiredApiPermissions": [
      {
        "resource": "Microsoft Graph",
        "delegatedPermissions": [
          "Mail.Send"
        ]
      }
    ]
  },
  "loaderConfig": {
    "internalModuleBaseUrls": [
      "<!-- PATH TO CDN -->"
    ],
    "entryModuleId": "send-email-web-part",
    "scriptResources": {
      "send-email-web-part": {
        "type": "path",
        "path": "send-email-web-part_35ff463a127e13c202f7.js"
      },
      "@microsoft/sp-property-pane": {
        "type": "component",
        "id": "f9e737b7-f0df-4597-ba8c-3060f82380db",
        "version": "1.13.1"
      },
      "SendEmailWebPartStrings": {
        "type": "path",
        "path": "SendEmailWebPartStrings_en-us_82f1959e0a759c8bdf989a015aa176ba.js"
      },
      "@microsoft/sp-core-library": {
        "type": "component",
        "id": "7263c7d0-1d6a-45ec-8d85-d4d1d234171b",
        "version": "1.13.1"
      },
      "@microsoft/sp-webpart-base": {
        "type": "component",
        "id": "974a7777-0990-4136-8fa6-95d80114c2e0",
        "version": "1.13.1"
      },
      "react": {
        "type": "component",
        "id": "0d910c1c-13b9-4e1c-9aa4-b008c5e42d7d",
        "version": "16.8.5"
      },
      "react-dom": {
        "type": "component",
        "id": "aa0a46ec-1505-43cd-a44a-93f3a5aa460a",
        "version": "16.8.5"
      }
    }
  }
}